rust_pyo3_timeseries-0.1.9.dist-info/METADATA
rust_pyo3_timeseries-0.1.9.dist-info/WHEEL
rust_pyo3_timeseries-0.1.9.dist-info/licenses/LICENSE
rust_pyo3_timeseries/__init__.py
rust_pyo3_timeseries/rust_pyo3_timeseries.cpython-312-darwin.so
rust_pyo3_timeseries-0.1.9.dist-info/RECORD
