Metadata-Version: 2.4
Name: rust_pyo3_timeseries
Version: 0.1.9
License-File: LICENSE
Summary: Rust-implemented time-series econometric utilities exposed to Python via PyO3.
Author: Dor Fuchs
License: MIT
Requires-Python: >=3.9
